methanal/__init__.py
methanal/_version.py
methanal/enums.py
methanal/errors.py
methanal/imethanal.py
methanal/model.py
methanal/publicpage.py
methanal/theme.py
methanal/util.py
methanal/view.py
methanal/widgets.py
methanal/js/Methanal/Deps.js
methanal/js/Methanal/Preds.js
methanal/js/Methanal/Util.js
methanal/js/Methanal/Validators.js
methanal/js/Methanal/View.js
methanal/js/Methanal/Widgets.js
methanal/js/Methanal/__init__.js
methanal/js/Methanal/Tests/MockBrowser.js
methanal/js/Methanal/Tests/TestMethanal.js
methanal/js/Methanal/Tests/TestPreds.js
methanal/js/Methanal/Tests/TestUtil.js
methanal/js/Methanal/Tests/TestValidators.js
methanal/js/Methanal/Tests/TestView.js
methanal/js/Methanal/Tests/TestWidgets.js
methanal/js/Methanal/Tests/Util.js
methanal/static/fonts/methanal-webfont.eot
methanal/static/fonts/methanal-webfont.svg
methanal/static/fonts/methanal-webfont.ttf
methanal/static/fonts/methanal-webfont.woff
methanal/static/images/collapse.png
methanal/static/images/expand.png
methanal/static/images/long-throbber.gif
methanal/static/images/main-throbber.gif
methanal/static/images/icons/close.png
methanal/static/styles/methanal-webfont.css
methanal/static/styles/methanal.css
methanal/test/__init__.py
methanal/test/test_enums.py
methanal/test/test_errors.py
methanal/test/test_javascript.py
methanal/test/test_model.py
methanal/test/test_util.py
methanal/test/test_view.py
methanal/test/test_widgets.py
methanal/themes/methanal-base/methanal-action-button.html
methanal/themes/methanal-base/methanal-action-container.html
methanal/themes/methanal-base/methanal-check-input.html
methanal/themes/methanal-base/methanal-expander-header.html
methanal/themes/methanal-base/methanal-expander.html
methanal/themes/methanal-base/methanal-filter-list.html
methanal/themes/methanal-base/methanal-form-row.html
methanal/themes/methanal-base/methanal-group.html
methanal/themes/methanal-base/methanal-liveform.html
methanal/themes/methanal-base/methanal-lookup.html
Methanal-0.9.0.dist-info/LICENSE
Methanal-0.9.0.dist-info/METADATA
Methanal-0.9.0.dist-info/WHEEL
Methanal-0.9.0.dist-info/top_level.txt
Methanal-0.9.0.dist-info/RECORD
