Metadata-Version: 2.1
Name: Methanal
Version: 0.9.0
Summary: A web forms library for Mantissa
Home-page: https://github.com/fusionapp/methanal
Maintainer: Methanal developers
License: UNKNOWN
Platform: UNKNOWN
Classifier: Development Status :: 4 - Beta
Classifier: Environment :: Web Environment
Classifier: Framework :: Twisted
Classifier: Intended Audience :: Developers
Classifier: License :: OSI Approved :: MIT License
Classifier: Operating System :: OS Independent
Classifier: Programming Language :: JavaScript
Classifier: Programming Language :: Python :: 2.7
Classifier: Topic :: Internet :: WWW/HTTP
Classifier: Topic :: Internet :: WWW/HTTP :: Dynamic Content
Classifier: Topic :: Software Development :: Libraries :: Python Modules
Requires-Dist: Twisted (>=2.5.0)
Requires-Dist: Epsilon (>=0.5.0)
Requires-Dist: Axiom (>=0.5.20)
Requires-Dist: Nevow (>=0.12.0)
Requires-Dist: Mantissa (>=0.6.1)
Requires-Dist: fusion-util (>=1.1.1)
